Metadata-Version: 1.0
Name: Remembrall
Version: 0.0.3
Summary: A terminal to-do list that reminds!
Home-page: UNKNOWN
Author: Saurabh AV
Author-email: saurabhav.torres@gmail.com
License: BSD
Keywords: remembrall to-do list
Platform: UNKNOWN
